Week - 5/1x8 demux/1x8demux.sv
module demux_1to8 (input in, input [2:0] sel, output reg [7:0] out);

always @ (sel or in) begin
    if (in === 1'b1) begin
        if (sel === 3'b000) begin
            out = 8'b00000001;
        end else if (sel === 3'b001) begin
            out = 8'b00000010;
        end else if (sel === 3'b010) begin
            out = 8'b00000100;
        end else if (sel === 3'b011) begin
            out = 8'b00001000;
        end else if (sel === 3'b100) begin
            out = 8'b00010000;
        end else if (sel === 3'b101) begin
            out = 8'b00100000;
        end else if (sel === 3'b110) begin
            out = 8'b01000000;
        end else if (sel === 3'b111) begin
            out = 8'b10000000;
        end else begin
            out = 8'b00000000;
        end
    end else begin
        out = 1'b0;
    end
end

endmodule

Week - 5/1x8 demux/1x8demuxTB.sv
module demux_1to8_tb;

reg in;
reg [2:0] sel;
wire [7:0] out;

demux_1to8 dut(in, sel, out);

initial begin
    $monitor("in: %b, sel: %b, out: %b", in, sel, out); 
    $dumpfile("dump.vcd"); $dumpvars(1);
    in = 1'b0; sel = 3'b000; #10;
    in = 1'b1; sel = 3'b001; #10;
    in = 1'b0; sel = 3'b010; #10;
    in = 1'b1; sel = 3'b011; #10;
    in = 1'b0; sel = 3'b100; #10;
    in = 1'b1; sel = 3'b101; #10;
    in = 1'b0; sel = 3'b110; #10;
    in = 1'b1; sel = 3'b111; #10;
    $finish;
end

endmodule

Week - 5/1x8 demux/dump.vcd
$date
	Mon May 29 16:34:49 2023
$end
$version
	Icarus Verilog
$end
$timescale
	1s
$end
$scope module demux_1to8_tb $end
$var wire 8 ! out [7:0] $end
$var reg 1 " in $end
$var reg 3 # sel [2:0] $end
$upscope $end
$enddefinitions $end
$comment Show the parameter values. $end
$dumpall
$end
#0
$dumpvars
b0 #
0"
b0 !
$end
#10
b10 !
b1 #
1"
#20
b0 !
b10 #
0"
#30
b1000 !
b11 #
1"
#40
b0 !
b100 #
0"
#50
b100000 !
b101 #
1"
#60
b0 !
b110 #
0"
#70
b10000000 !
b111 #
1"
