Week - 2/full subtractor/fullAdder.sv
module myFullAdder(input1, input2, input3, sum, carry);
    input input1, input2, input3;
    output sum, carry;
    wire xor12;

    assign xor12 = input1 ^ input2;
    assign sum = xor12 ^ input3;
    assign carry = (input1 & input2) | (xor12 & input3);
endmodule

full subtractor/fullAdderTB.sv
module fullAdderTB;
    reg input1, input2, input3;
    wire sum, carry;
    myFullAdder fullAdderTB(.input1(input1), .input2(input2), .input3(input3), .sum(sum), .carry(carry));
        initial begin
            $dumpfile("dump.vcd");
            $dumpvars(1);

            input1 = 1'b0;
            input2 = 1'b0;
            input3 = 1'b0;
            #1 $display("Input1: %b, Input2: %b, Input3 (c-in): %b, Sum: %b, Carry: %b", input1, input2, input3, sum, carry);

            input1 = 1'b0;
            input2 = 1'b0;
            input3 = 1'b1;
            #1 $display("Input1: %b, Input2: %b, Input3 (c-in): %b, Sum: %b, Carry: %b", input1, input2, input3, sum, carry);

            input1 = 1'b0;
            input2 = 1'b1;
            input3 = 1'b0;
            #1 $display("Input1: %b, Input2: %b, Input3 (c-in): %b, Sum: %b, Carry: %b", input1, input2, input3, sum, carry);

            input1 = 1'b0;
            input2 = 1'b1;
            input3 = 1'b1;
            #1 $display("Input1: %b, Input2: %b, Input3 (c-in): %b, Sum: %b, Carry: %b", input1, input2, input3, sum, carry);

            input1 = 1'b1;
            input2 = 1'b0;
            input3 = 1'b0;
            #1 $display("Input1: %b, Input2: %b, Input3 (c-in): %b, Sum: %b, Carry: %b", input1, input2, input3, sum, carry);

            input1 = 1'b1;
            input2 = 1'b0;
            input3 = 1'b1;
            #1 $display("Input1: %b, Input2: %b, Input3 (c-in): %b, Sum: %b, Carry: %b", input1, input2, input3, sum, carry);

            input1 = 1'b1;
            input2 = 1'b1;
            input3 = 1'b0;
            #1 $display("Input1: %b, Input2: %b, Input3 (c-in): %b, Sum: %b, Carry: %b", input1, input2, input3, sum, carry);

            input1 = 1'b1;
            input2 = 1'b1;
            input3 = 1'b1;
            #1 $display("Input1: %b, Input2: %b, Input3 (c-in): %b, Sum: %b, Carry: %b", input1, input2, input3, sum, carry);
        end
endmodule

Week - 2/full adder/dump.vcd
$date
	Tue Mar 07 11:12:30 2023
$end
$version
	Icarus Verilog
$end
$timescale
	1s
$end
$scope module fullAdderTB $end
$var wire 1 ! sum $end
$var wire 1 " carry $end
$var reg 1 # input1 $end
$var reg 1 $ input2 $end
$var reg 1 % input3 $end
$upscope $end
$enddefinitions $end
$comment Show the parameter values. $end
$dumpall
$end
#0
$dumpvars
0%
0$
0#
0"
0!
$end
#1
1!
1%
#2
0%
1$
#3
1"
0!
1%
#4
0"
1!
0%
0$
1#
#5
1"
0!
1%
#6
0%
1$
#7
1!
1%
