Week - 2/full adder/fullAdder.sv
module myFullAdder(X, Y, cin, sum, cout);
    input X, Y, cin;
    output sum, cout;
    wire xor12;

    assign xor12 = X ^ Y;
    assign sum = xor12 ^ cin;
    assign cout = (X & Y) | (xor12 & cin);
endmodule

Week - 2/full adder/fullAdderTB.sv
module fullAdderTB;
    reg X, Y, cin;
    wire sum, cout;
    myFullAdder fullAdderTB(.X(X), .Y(Y), .cin(cin), .sum(sum), .cout(cout));
        initial begin
            $monitor("X: %b, Y: %b, cin: %b, sum: %b, cout: %b", X, Y, cin, sum, cout);
            $dumpfile("dump.vcd"); $dumpvars;
            X = 1'b0; Y = 1'b0; cin = 1'b0; #10;
            X = 1'b0; Y = 1'b0; cin = 1'b1; #10;
            X = 1'b0; Y = 1'b1; cin = 1'b0; #10;
            X = 1'b0; Y = 1'b1; cin = 1'b1; #10;
            X = 1'b1; Y = 1'b0; cin = 1'b0; #10;
            X = 1'b1; Y = 1'b0; cin = 1'b1; #10;
            X = 1'b1; Y = 1'b1; cin = 1'b0; #10;
            X = 1'b1; Y = 1'b1; cin = 1'b1; #10;
            $finish;
        end
endmodule

Week - 2/full adder/dump.vcd
$date
	Mon May 29 17:01:20 2023
$end
$version
	Icarus Verilog
$end
$timescale
	1s
$end
$scope module fullAdderTB $end
$var wire 1 ! sum $end
$var wire 1 " cout $end
$var reg 1 # X $end
$var reg 1 $ Y $end
$var reg 1 % cin $end
$scope module fullAdderTB $end
$var wire 1 # X $end
$var wire 1 $ Y $end
$var wire 1 % cin $end
$var wire 1 " cout $end
$var wire 1 ! sum $end
$var wire 1 & xor12 $end
$upscope $end
$upscope $end
$enddefinitions $end
$comment Show the parameter values. $end
$dumpall
$end
#0
$dumpvars
0&
0%
0$
0#
0"
0!
$end
#10
1!
1%
#20
1&
0%
1$
#30
1"
0!
1%
#40
0"
1!
0%
0$
1#
#50
1"
0!
1%
#60
0&
0%
1$
#70
1!
1%
