Week - 8/SIPO/SIPO.sv
module sipo(d, clk, d0);
    input d,clk;
    output reg [3:0]d0 = 1'b0000;
    always @(posedge clk) begin
        d0[3] <= d;
        d0[2] <= d0[3];
        d0[1] <= d0[2];
        d0[0] <= d0[1];
    end
endmodule

Week - 8/SIPO/SIPOTB.sv
module testbench();
    reg d, clk;
    wire [3:0] d0;
    sipo a(.d(d), .clk(clk), .d0(d0));

    initial begin
        $dumpfile("dump.vcd");
        $dumpvars(1);
        $monitor($time, " d=%b, clk=%b, d0=%b", d, clk, d0);
    end

    initial begin
        clk = 1'b0;
        forever #5 clk = ~clk;
    end

    initial begin
        d = 1;
        #10 d = 0;
        #10 d = 1;
        #10 d = 1;
        #40 $finish;
    end
endmodule

Week - 8/SIPO/dump.vcd
$date
	Mon May 29 21:36:36 2023
$end
$version
	Icarus Verilog
$end
$timescale
	1s
$end
$scope module testbench $end
$var wire 4 ! d0 [3:0] $end
$var reg 1 " clk $end
$var reg 1 # d $end
$upscope $end
$enddefinitions $end
$comment Show the parameter values. $end
$dumpall
$end
#0
$dumpvars
1#
0"
b0 !
$end
#5
b1000 !
1"
#10
0"
0#
#15
b100 !
1"
#20
0"
1#
#25
b1010 !
1"
#30
0"
#35
b1101 !
1"
#40
0"
#45
b1110 !
1"
#50
0"
#55
b1111 !
1"
