3x8 decoder/decoder.sv
module decoder (input A0, A1, A2, output D0, D1, D2, D3, D4, D5, D6, D7);
    assign D0 = ~A0 & ~A1 & ~A2;
    assign D1 = ~A0 & ~A1 & A2;
    assign D2 = ~A0 & A1 & ~A2;
    assign D3 = ~A0 & A1 & A2;
    assign D4 = A0 & ~A1 & ~A2;
    assign D5 = A0 & ~A1 & A2;
    assign D6 = A0 & A1 & ~A2;
    assign D7 = A0 & A1 & A2;
endmodule

Week - 4/3x8 decoder/decoderTB.sv
module decoder_tb;
  reg A0, A1, A2;
  wire D0, D1, D2, D3, D4, D5, D6, D7;
  decoder dut (.A0(A0), .A1(A1), .A2(A2), .D0(D0), .D1(D1), .D2(D2), .D3(D3), .D4(D4), .D5(D5), .D6(D6), .D7(D7));

  initial begin
    $monitor("A0: %b, A1: %b, A2: %b", A0, A1, A2,
    "\nD0: %b, D1: %b, D2: %b, D3: %b", D0, D1, D2, D3,
    "\nD4: %b, D5: %b, D6: %b, D7: %b\n", D4, D5, D6, D7);
    $dumpfile("dump.vcd"); $dumpvars(1);
    A0 = 0; A1 = 0; A2 = 0;
    #20 A0 = 0; A1 = 0; A2 = 1;
    #20 A0 = 0; A1 = 1; A2 = 0;
    #20 A0 = 0; A1 = 1; A2 = 1;
    #20 A0 = 1; A1 = 0; A2 = 0;
    #20 A0 = 1; A1 = 0; A2 = 1;
    #20 A0 = 1; A1 = 1; A2 = 0;
    #20 A0 = 1; A1 = 1; A2 = 1;
    #20;
    $finish;
  end

endmodule

Week - 4/3x8 decoder/dump.vcd
$date
	Mon May 29 16:18:50 2023
$end
$version
	Icarus Verilog
$end
$timescale
	1s
$end
$scope module decoder_tb $end
$var wire 1 ! D7 $end
$var wire 1 " D6 $end
$var wire 1 # D5 $end
$var wire 1 $ D4 $end
$var wire 1 % D3 $end
$var wire 1 & D2 $end
$var wire 1 ' D1 $end
$var wire 1 ( D0 $end
$var reg 1 ) A0 $end
$var reg 1 * A1 $end
$var reg 1 + A2 $end
$upscope $end
$enddefinitions $end
$comment Show the parameter values. $end
$dumpall
$end
#0
$dumpvars
0+
0*
0)
1(
0'
0&
0%
0$
0#
0"
0!
$end
#20
0(
1'
1+
#40
1&
0'
0+
1*
#60
0&
1%
1+
#80
1$
0%
0+
0*
1)
#100
0$
1#
1+
#120
1"
0#
0+
1*
#140
0"
1!
1+
