Week - 5/8x1 mux/8x1mux.sv
module mux8X1 (input [7:0]in, input [2:0]sel, output reg out);
    always @(*) begin
        if (sel === 2'b000) begin
            out = in[0];
        end else if (sel === 'b001) begin
            out = in[1];
        end else if (sel === 'b010) begin
            out = in[2];
        end else if (sel === 'b011) begin
            out = in[3];
        end else if (sel === 'b100) begin
            out = in[4];
        end else if (sel === 'b101) begin
            out = in[5];
        end else if (sel === 'b110) begin
            out = in[6];
        end else if (sel === 'b111) begin
            out = in[7];
        end
    end
endmodule

Week - 5/8x1 mux/8x1muxTB.sv
module mux8X1_tb;
    reg [7:0]in;
    reg [2:0]sel;
    wire out;

    mux8X1 uut (.in(in), .sel(sel), .out(out));

    initial begin
        $monitor("in: %b | sel: %b | out: %b", in, sel, out);
        $dumpfile("dump.vcd"); $dumpvars(1);
            in = 'b1; sel = 'b0; #10;
            in = 'b0; sel = 'b0; #10;
            in = 'b10; sel = 'b1; #10;
            in = 'b0; sel = 'b1; #10;
            in = 'b100; sel = 'b10; #10;
            in = 'b0; sel = 'b10; #10;
            in = 'b1000; sel = 'b11; #10;
            in = 'b0; sel = 'b11; #10;
            in = 'b10000; sel = 'b100; #10;
            in = 'b0; sel = 'b100; #10;
            in = 'b100000; sel = 'b101; #10;
            in = 'b0; sel = 'b101; #10;
            in = 'b1000000; sel = 'b110; #10;
            in = 'b0; sel = 'b110; #10;
            in = 'b10000000; sel = 'b111; #10;
            in = 'b0; sel = 'b111; #10;
        $finish;
    end
endmodule

Week - 5/8x1 mux/dump.vcd
$date
	Mon May 29 17:06:08 2023
$end
$version
	Icarus Verilog
$end
$timescale
	1s
$end
$scope module mux8X1_tb $end
$var wire 1 ! out $end
$var reg 8 " in [7:0] $end
$var reg 3 # sel [2:0] $end
$upscope $end
$enddefinitions $end
$comment Show the parameter values. $end
$dumpall
$end
#0
$dumpvars
b0 #
b1 "
1!
$end
#10
0!
b0 "
#20
1!
b1 #
b10 "
#30
0!
b0 "
#40
1!
b10 #
b100 "
#50
0!
b0 "
#60
1!
b11 #
b1000 "
#70
0!
b0 "
#80
1!
b100 #
b10000 "
#90
0!
b0 "
#100
1!
b101 #
b100000 "
#110
0!
b0 "
#120
1!
b110 #
b1000000 "
#130
0!
b0 "
#140
1!
b111 #
b10000000 "
#150
0!
b0 "
