Week - 10/Ring counter/ringcounter.sv
module ringcounter (clk, reset, Count_out);

  input clk, reset;
  output [3:0] Count_out;
  reg [3:0] Count_temp;

  always @(posedge clk or reset) begin
    if (reset) begin
      Count_temp <= 4'b0001;
    end
    else if (clk) begin
      Count_temp <= {Count_temp[2:0], Count_temp[3]};
    end
  end

  assign Count_out = Count_temp;

endmodule

Week - 10/Ring counter/rcTB.sv
module tb_ringcounter;

  reg clk, Reset;
  wire [3:0] Count_out;

  ringcounter dut (
    .clk(clk),
    .reset(Reset),
    .Count_out(Count_out)
  );

  always #5 clk = ~clk;

  initial begin
    $dumpfile("dump.vcd"); $dumpvars(1);
    clk = 0;
    Reset = 1;
    #10 Reset = 0;
    #60 $finish;
  end

  always @(posedge clk) begin
    $display("count: %d", Count_out);
  end

endmodule

Week - 10/Ring counter/dump.vcd
$date
	Mon May 29 22:51:39 2023
$end
$version
	Icarus Verilog
$end
$timescale
	1s
$end
$scope module tb_ringcounter $end
$var wire 4 ! Count_out [3:0] $end
$var reg 1 " Reset $end
$var reg 1 # clk $end
$upscope $end
$enddefinitions $end
$comment Show the parameter values. $end
$dumpall
$end
#0
$dumpvars
0#
1"
b1 !
$end
#5
1#
#10
0#
0"
#15
b10 !
1#
#20
0#
#25
b100 !
1#
#30
0#
#35
b1000 !
1#
#40
0#
#45
b1 !
1#
#50
0#
#55
b10 !
1#
#60
0#
#65
b100 !
1#
