Week - 9/4-bit updown counter/updownc.sv
module BCDupdown (
  input Clk,
  input rst,
  input UpOrDown,
  output reg [3:0] Count = 0
);

  always @(posedge Clk) begin
    if (rst == 1) begin
      Count <= 0;
    end
    else begin
      if (UpOrDown == 1) begin
        if (Count == 15) begin
          Count <= 0;
        end
        else begin
          Count <= Count + 1;
        end
      end
      else begin
        if (Count == 0) begin
          Count <= 15;
        end
        else begin
          Count <= Count - 1;
        end
      end
    end
  end
  
endmodule

Week - 9/4-bit updown counter/updownTB.sv
module BCDupdown_tb;
  
  reg Clk, rst, UpOrDown;
  wire [3:0] Count;
  
  BCDupdown dut (.Clk(Clk), .rst(rst), .UpOrDown(UpOrDown), .Count(Count));
  
  always #5 Clk = ~Clk;
  
  initial begin
    $dumpfile("dump.vcd"); $dumpvars(1);
    Clk = 0; rst = 0; UpOrDown = 1;
    rst = 1; #10 rst = 0;
    #20 UpOrDown = 1;
    #40 UpOrDown = 0;
    #40 $finish;
  end
  
  always @(posedge Clk) $display("Count: %d", Count);
  
endmodule

Week - 9/4-bit updown counter/dump.vcd
$date
	Mon May 29 22:22:01 2023
$end
$version
	Icarus Verilog
$end
$timescale
	1s
$end
$scope module BCDupdown_tb $end
$var wire 4 ! Count [3:0] $end
$var reg 1 " Clk $end
$var reg 1 # UpOrDown $end
$var reg 1 $ rst $end
$upscope $end
$enddefinitions $end
$comment Show the parameter values. $end
$dumpall
$end
#0
$dumpvars
1$
1#
0"
b0 !
$end
#5
1"
#10
0"
0$
#15
b1 !
1"
#20
0"
#25
b10 !
1"
#30
0"
#35
b11 !
1"
#40
0"
#45
b100 !
1"
#50
0"
#55
b101 !
1"
#60
0"
#65
b110 !
1"
#70
0"
0#
#75
b101 !
1"
#80
0"
#85
b100 !
1"
#90
0"
#95
b11 !
1"
#100
0"
#105
b10 !
1"
