Week - 2/full subtractor/fullSub.sv
module full_subtractor(input a, b, bin, output diff, bout);
    assign diff = a ^ b ^ bin;
    assign bout = (~a & b & bin) | (a & ~b & ~bin);
endmodule

Week - 2/full subtractor/fullSubTB.sv
module full_subtractor_tb;
    reg a, b, bin;
    wire diff, bout;

    full_subtractor fs(a, b, bin, diff, bout);

    initial begin
        $monitor("a = %b, b = %b, bin = %b, diff = %b, bout = %b",
                 a, b, bin, diff, bout);
        $dumpfile("dump.vcd"); $dumpvars;
        a = 0; b = 0; bin = 0; #10;
        a = 0; b = 0; bin = 1; #10;
        a = 0; b = 1; bin = 0; #10;
        a = 0; b = 1; bin = 1; #10;
        a = 1; b = 0; bin = 0; #10;
        a = 1; b = 0; bin = 1; #10;
        a = 1; b = 1; bin = 0; #10;
        a = 1; b = 1; bin = 1; #10;
        $finish;
    end
endmodule

Week - 2/full subtractor/dump.vcd
$date
	Mon May 29 17:02:09 2023
$end
$version
	Icarus Verilog
$end
$timescale
	1s
$end
$scope module full_subtractor_tb $end
$var wire 1 ! diff $end
$var wire 1 " bout $end
$var reg 1 # a $end
$var reg 1 $ b $end
$var reg 1 % bin $end
$scope module fs $end
$var wire 1 # a $end
$var wire 1 $ b $end
$var wire 1 % bin $end
$var wire 1 " bout $end
$var wire 1 ! diff $end
$upscope $end
$upscope $end
$enddefinitions $end
$comment Show the parameter values. $end
$dumpall
$end
#0
$dumpvars
0%
0$
0#
0"
0!
$end
#10
1!
1%
#20
0%
1$
#30
1"
0!
1%
#40
1!
0%
0$
1#
#50
0"
0!
1%
#60
0%
1$
#70
1!
1%
