Week - 10/Johnson counter/johnsoncounter.sv
module johnsoncounter (clk, reset, Count_out);

  input clk, reset;
  output [3:0] Count_out;
  reg [3:0] Count_temp;

  always @(posedge clk or reset) begin
    if (reset) begin
      Count_temp <= 4'b0000;
    end
    else if (clk) begin
      Count_temp <= {Count_temp[2:0], ~Count_temp[3]};
    end
  end

  assign Count_out = Count_temp;

endmodule

Week - 10/Johnson counter/jcTB.sv
module tb_johnsoncounter;

  reg clk, reset;
  wire [3:0] Count_out;

  johnsoncounter dut (
    .clk(clk),
    .reset(reset),
    .Count_out(Count_out)
  );

  always #5 clk = ~clk;

  initial begin
    $dumpfile("dump.vcd"); $dumpvars(1);
    clk = 0;
    reset = 1;
    #10 reset = 0;
    #80 $finish;
  end

  always @(posedge clk) begin
    $display("count: %d", Count_out);
  end

endmodule

Week - 10/Johnson counter/dump.vcd
$date
	Mon May 29 22:52:20 2023
$end
$version
	Icarus Verilog
$end
$timescale
	1s
$end
$scope module tb_johnsoncounter $end
$var wire 4 ! Count_out [3:0] $end
$var reg 1 " clk $end
$var reg 1 # reset $end
$upscope $end
$enddefinitions $end
$comment Show the parameter values. $end
$dumpall
$end
#0
$dumpvars
1#
0"
b0 !
$end
#5
1"
#10
0"
0#
#15
b1 !
1"
#20
0"
#25
b11 !
1"
#30
0"
#35
b111 !
1"
#40
0"
#45
b1111 !
1"
#50
0"
#55
b1110 !
1"
#60
0"
#65
b1100 !
1"
#70
0"
#75
b1000 !
1"
#80
0"
#85
b0 !
1"
